template_model/VERSION.md
template_model/__init__.py
template_model/admin.py
template_model/apps.py
template_model/forms.py
template_model/models.py
template_model/serializers.py
template_model/urls.py
template_model/views.py
template_model/migrations/0001_initial.py
template_model/migrations/0002_text_to_file_field.py
template_model/migrations/__init__.py
template_model/tests/__init__.py
template_model/tests/settings.py
template_model/tests/test_forms.py
template_model/tests/test_models.py
template_model/tests/test_serializers.py
template_model/tests/test_template_view_set_content.py
test_template_model/__init__.py
test_template_model/settings.py
test_template_model/urls.py
test_template_model/wsgi.py
django_template_model-1.0.0.dist-info/LICENSE
django_template_model-1.0.0.dist-info/METADATA
django_template_model-1.0.0.dist-info/WHEEL
django_template_model-1.0.0.dist-info/top_level.txt
django_template_model-1.0.0.dist-info/RECORD
